{
  "entityType" : "NOTIFICATION_RULE",
  "entity" : {
    "additionalConfig" : {
      "description" : "Send notification to tenant admins when device is created"
    },
    "enabled" : true,
    "externalId" : null,
    "id" : {
      "entityType" : "NOTIFICATION_RULE",
      "id" : "36d07660-0252-11ef-bb7c-694ba8f400e9"
    },
    "name" : "Device created",
    "recipientsConfig" : {
      "targets" : [ "36c61620-0252-11ef-bb7c-694ba8f400e9" ],
      "triggerType" : "ENTITY_ACTION"
    },
    "templateId" : {
      "entityType" : "NOTIFICATION_TEMPLATE",
      "id" : "36cf3de0-0252-11ef-bb7c-694ba8f400e9"
    },
    "triggerConfig" : {
      "triggerType" : "ENTITY_ACTION",
      "created" : true,
      "deleted" : false,
      "entityTypes" : [ "DEVICE" ],
      "updated" : false,
      "triggerType" : "ENTITY_ACTION"
    },
    "triggerType" : "ENTITY_ACTION"
  },
  "relations" : [ ],
  "attributes" : {
    "SERVER_SCOPE" : [ ]
  }
}